carcinize/__init__.py
carcinize/_base.py
carcinize/_exceptions.py
carcinize/_iter.py
carcinize/_lazy.py
carcinize/_option.py
carcinize/_result.py
carcinize/_string.py
carcinize/_struct.py
carcinize/py.typed
carcinize-0.1.5.dist-info/WHEEL
carcinize-0.1.5.dist-info/METADATA
carcinize-0.1.5.dist-info/RECORD
