Metadata-Version: 2.4
Name: carcinize
Version: 0.1.5
Summary: Make your python code a little bit rustier.
Author: Ron Leizrowice
Author-email: Ron Leizrowice <ron.leizrowice@protonmail.com>
License-Expression: WTFPL
Classifier: Programming Language :: Python :: 3 :: Only
Classifier: Programming Language :: Python :: 3.13
Classifier: Programming Language :: Python :: 3.14
Requires-Dist: pydantic>=2
Requires-Dist: pydantic-core>=2
Requires-Python: >=3.13
